winocr.py
winocr-0.0.15.dist-info/LICENSE
winocr-0.0.15.dist-info/METADATA
winocr-0.0.15.dist-info/WHEEL
winocr-0.0.15.dist-info/entry_points.txt
winocr-0.0.15.dist-info/top_level.txt
winocr-0.0.15.dist-info/RECORD
