Metadata-Version: 2.1
Name: winocr
Version: 0.0.15
Summary: Windows.Media.Ocr
Home-page: https://github.com/GitHub30/winocr
Author: Tomofumi Inoue
Author-email: funaox@gmail.com
Project-URL: Bug Tracker, https://github.com/GitHub30/winocr/issues
Classifier: Programming Language :: Python :: 3
Classifier: License :: OSI Approved :: MIT License
Classifier: Operating System :: Microsoft :: Windows :: Windows 10
License-File: LICENSE
Requires-Dist: winrt-windows-foundation-collections
Requires-Dist: winrt-windows-foundation
Requires-Dist: winrt-windows-globalization
Requires-Dist: winrt-windows-graphics-imaging
Requires-Dist: winrt-windows-media-ocr
Requires-Dist: winrt-windows-storage-streams
Provides-Extra: all
Requires-Dist: Pillow; extra == "all"
Requires-Dist: fastapi; extra == "all"
Requires-Dist: uvicorn; extra == "all"
Requires-Dist: opencv-python; extra == "all"
Provides-Extra: api
Requires-Dist: Pillow; extra == "api"
Requires-Dist: fastapi; extra == "api"
Requires-Dist: uvicorn; extra == "api"
Provides-Extra: cv2
Requires-Dist: opencv-python; extra == "cv2"
